vesper_birdvox/__init__.py
vesper_birdvox/run_birdvoxdetect.py
vesper_birdvox/version.py
vesper_birdvox-1.0.0.dist-info/LICENSE
vesper_birdvox-1.0.0.dist-info/METADATA
vesper_birdvox-1.0.0.dist-info/WHEEL
vesper_birdvox-1.0.0.dist-info/entry_points.txt
vesper_birdvox-1.0.0.dist-info/top_level.txt
vesper_birdvox-1.0.0.dist-info/RECORD
