Metadata-Version: 2.1
Name: vesper-birdvox
Version: 1.0.0
Summary: Software for interfacing Vesper with BirdVoxDetect.
Home-page: https://github.com/HaroldMills/vesper-birdvox
Author: Harold Mills
Author-email: harold.mills@gmail.com
License: MIT
Platform: UNKNOWN
Classifier: Programming Language :: Python :: 3
Classifier: Operating System :: OS Independent
Classifier: License :: OSI Approved :: MIT License
Requires-Dist: birdvoxdetect (>=0.2)
